doctrans/__init__.py
doctrans/__main__.py
doctrans/format_converter.py
doctrans/fonts/apple_sd_gothic.ttf
doctrans/fonts/hy_shinmyeongjo.ttf
doctrans/fonts/malgun_gothic.ttf
doctrans/fonts/nanum_gothic.ttf
doctrans/fonts/times_new_roman.ttf
doctrans/lang/__init__.py
doctrans/lang/google.py
doctrans/lang/kakao.py
doctrans/models/__init__.py
doctrans/models/option.py
doctrans/models/translator.py
doctrans/models/pydocx/__init__.py
doctrans/models/pydocx/docxcontents.py
doctrans/models/pydocx/parsers.py
doctrans/models/pydocx/tokenizer.py
doctrans/models/pydocx/translator.py
doctrans/models/pymupdf/__init__.py
doctrans/models/pymupdf/translator.py
doctrans-0.0.3.dist-info/LICENSE
doctrans-0.0.3.dist-info/METADATA
doctrans-0.0.3.dist-info/WHEEL
doctrans-0.0.3.dist-info/top_level.txt
doctrans-0.0.3.dist-info/RECORD
