Metadata-Version: 2.1
Name: doctrans
Version: 0.0.3
Summary: Translate only the main text in the document
Home-page: https://github.com/calvin0627/pdf-translator
Author: calvin0627
Author-email: calvin0627@naver.com
License: MIT
Platform: UNKNOWN
Classifier: Programming Language :: Python :: 3.7
Classifier: License :: OSI Approved :: MIT License
Classifier: Operating System :: OS Independent
Requires-Python: >=3
Requires-Dist: google-trans-new (==1.1.9)
Requires-Dist: kakaotrans (==0.1.2)
Requires-Dist: pywin32 (==300)
Requires-Dist: python-docx
Requires-Dist: nltk (==3.5)
Requires-Dist: requests
Requires-Dist: PyMuPDF (==1.18.6)
Requires-Dist: click
